{
  "project_info": {
    "project_number": "386564109367",
    "project_id": "fitness-uygulamasi-7940b",
    "storage_bucket": "fitness-uygulamasi-7940b.appspot.com"
  },
  "client": [
    {
      "client_info": {
        "mobilesdk_app_id": "1:386564109367:android:a484d260e1d73a9ce8bbb2",
        "android_client_info": {
          "package_name": "com.example.fitnessuygulamasi"
        }
      },
      "oauth_client": [
        {
          "client_id": "386564109367-vu8ufdsnpe79kscpsaqe7jhi07lb12i5.apps.googleusercontent.com",
          "client_type": 3
        }
      ],
      "api_key": [
        {
          "current_key": "AIzaSyDhP_3RRCu5BUKTu6Yvn5aVQPimRFLg8BQ"
        }
      ],
      "services": {
        "appinvite_service": {
          "other_platform_oauth_client": [
            {
              "client_id": "386564109367-vu8ufdsnpe79kscpsaqe7jhi07lb12i5.apps.googleusercontent.com",
              "client_type": 3
            }
          ]
        }
      }
    }
  ],
  "configuration_version": "1"
}